htpymodule/__init__.py
htpymodule/add.py
htpymodule/subtract.py
htpymodule-0.3.1.dist-info/METADATA
htpymodule-0.3.1.dist-info/WHEEL
htpymodule-0.3.1.dist-info/top_level.txt
htpymodule-0.3.1.dist-info/RECORD
